huaweicloudsdkugo/__init__.py
huaweicloudsdkugo/v1/__init__.py
huaweicloudsdkugo/v1/ugo_async_client.py
huaweicloudsdkugo/v1/ugo_client.py
huaweicloudsdkugo/v1/model/__init__.py
huaweicloudsdkugo/v1/model/check_permission_request.py
huaweicloudsdkugo/v1/model/check_permission_response.py
huaweicloudsdkugo/v1/model/commit_syntax_conversion_request.py
huaweicloudsdkugo/v1/model/commit_syntax_conversion_response.py
huaweicloudsdkugo/v1/model/commit_verification_request.py
huaweicloudsdkugo/v1/model/commit_verification_response.py
huaweicloudsdkugo/v1/model/confirm_target_db_req.py
huaweicloudsdkugo/v1/model/confirm_target_db_type_request.py
huaweicloudsdkugo/v1/model/confirm_target_db_type_response.py
huaweicloudsdkugo/v1/model/create_evaluation_project_req.py
huaweicloudsdkugo/v1/model/create_evaluation_project_request.py
huaweicloudsdkugo/v1/model/create_evaluation_project_response.py
huaweicloudsdkugo/v1/model/create_migration_project.py
huaweicloudsdkugo/v1/model/create_migration_project_request.py
huaweicloudsdkugo/v1/model/create_migration_project_response.py
huaweicloudsdkugo/v1/model/data_base.py
huaweicloudsdkugo/v1/model/database_object.py
huaweicloudsdkugo/v1/model/delete_evaluation_project_request.py
huaweicloudsdkugo/v1/model/delete_evaluation_project_response.py
huaweicloudsdkugo/v1/model/delete_migration_project_request.py
huaweicloudsdkugo/v1/model/delete_migration_project_response.py
huaweicloudsdkugo/v1/model/download_failure_report_request.py
huaweicloudsdkugo/v1/model/download_failure_report_response.py
huaweicloudsdkugo/v1/model/evaluation_project.py
huaweicloudsdkugo/v1/model/list_api_versions_request.py
huaweicloudsdkugo/v1/model/list_api_versions_response.py
huaweicloudsdkugo/v1/model/list_evaluation_projects_request.py
huaweicloudsdkugo/v1/model/list_evaluation_projects_response.py
huaweicloudsdkugo/v1/model/list_migration_projects_request.py
huaweicloudsdkugo/v1/model/list_migration_projects_response.py
huaweicloudsdkugo-3.1.184.dist-info/METADATA
huaweicloudsdkugo-3.1.184.dist-info/WHEEL
huaweicloudsdkugo-3.1.184.dist-info/licenses/LICENSE
huaweicloudsdkugo-3.1.184.dist-info/RECORD
